MANIFEST.in
setup.cfg
setup.py
bin/kata-scrape
kata_scrape/__init__.py
kata_scrape/client.py
kata_scrape/main.py
kata_scrape/settings.py
kata_scrape.egg-info/PKG-INFO
kata_scrape.egg-info/SOURCES.txt
kata_scrape.egg-info/dependency_links.txt
kata_scrape.egg-info/not-zip-safe
kata_scrape.egg-info/requires.txt
kata_scrape.egg-info/top_level.txt
kata_scrape/templates/config.example.json
kata_scrape/templates/description.md.j2
kata_scrape/templates/code/javascript.j2
kata_scrape/templates/code/python.j2
kata_scrape/templates/code/ruby.j2
kata_scrape/templates/fixture/javascript.j2
kata_scrape/templates/fixture/package.json
kata_scrape/templates/fixture/python.j2
kata_scrape/templates/fixture/ruby.j2
kata_scrape/test_utils/javascript/chai-display.js
kata_scrape/test_utils/javascript/display.js
kata_scrape/test_utils/javascript/test_utils.js
kata_scrape/test_utils/python/test_utils.py
kata_scrape/test_utils/ruby/common.rb
kata_scrape/test_utils/ruby/test_utils.rb