Metadata-Version: 1.0
Name: kata-scrape
Version: 0.2
Summary: A simple client for scraping Codewars katas
Home-page: https://github.com/jstoebel/kata_scrape
Author: Jacob Stoebel
Author-email: jstoebel@gmail.com
License: MIT
Keywords: codewars,code katas,selenium
Platform: UNKNOWN
